README.rst
pyproject.toml
setup.py
bin/nixts
nixts/__init__.py
nixts/client.py
nixts/disk.py
nixts/engine.py
nixts/errors.py
nixts/fleet.py
nixts/object.py
nixts/persist.py
nixts/serial.py
nixts/thread.py
nixts/timer.py
nixts/utility.py
nixts.egg-info/PKG-INFO
nixts.egg-info/SOURCES.txt
nixts.egg-info/dependency_links.txt
nixts.egg-info/top_level.txt
nixts/modules/__init__.py
nixts/modules/dbg.py
nixts/modules/err.py
nixts/modules/flt.py
nixts/modules/fnd.py
nixts/modules/irc.py
nixts/modules/log.py
nixts/modules/mod.py
nixts/modules/req.py
nixts/modules/rss.py
nixts/modules/slg.py
nixts/modules/tbl.py
nixts/modules/tdo.py
nixts/modules/thr.py
nixts/modules/tmr.py
nixts/modules/upt.py
nixts/modules/ver.py
tests/test_composite.py
tests/test_handler.py
tests/test_interface.py
tests/test_json.py
tests/test_mixin.py
tests/test_none.py
tests/test_object.py