Metadata-Version: 2.4
Name: nixts
Version: 10
Summary: nixt modules
Author-email: Bart Thate <nixtniet@gmail.com>
License-Expression: Unlicense
Project-URL: home, https://pypi.org/project/nixts
Project-URL: bugs, https://github.com/nixtniet/nixts/issues
Project-URL: source, https://github.com/nixtniet/nixts
Classifier: Development Status :: 3 - Alpha
Classifier: Operating System :: Unix
Classifier: Programming Language :: Python :: 3
Classifier: Topic :: Utilities
